AUTHORS
CHANGELOG
LICENSE
MANIFEST.in
README.md
setup.py
jinjatag/__init__.py
jinjatag/__init__.pyc
jinjatag/decorators.py
jinjatag/decorators.pyc
jinjatag/extension.py
jinjatag/extension.pyc
jinjatag/version.py
jinjatag/version.pyc
jinjatag.egg-info/PKG-INFO
jinjatag.egg-info/SOURCES.txt
jinjatag.egg-info/dependency_links.txt
jinjatag.egg-info/requires.txt
jinjatag.egg-info/top_level.txt
jinjatag/tests/__init__.py
jinjatag/tests/__init__.pyc
jinjatag/tests/multiblock.py
jinjatag/tests/multiblock.pyc
jinjatag/tests/simpleblock.py
jinjatag/tests/simpleblock.pyc
jinjatag/tests/simpletag.py
jinjatag/tests/simpletag.pyc