Metadata-Version: 1.0
Name: jinjatag
Version: 0.1.6
Summary: A library to make Jinja2 Extensions Easy
Home-page: https://github.com/mankyd/jinjatag
Author: Dave Mankoff
Author-email: mankyd@gmail.com
License: GPLv3
Platform: UNKNOWN
Classifier: Development Status :: 3 - Alpha
Classifier: Environment :: Web Environment
Classifier: Intended Audience :: Developers
Classifier: License :: OSI Approved :: GNU General Public License (GPL)
Classifier: Operating System :: OS Independent
Classifier: Programming Language :: Python
Classifier: Programming Language :: Python :: 2.7
Classifier: Programming Language :: Python :: 2.6
